osscs/config.py
osscs/backend/client/__init__.py
osscs/backend/client/message_sender.py
osscs/backend/client/common/__init__.py
osscs/backend/client/common/base_message_sender.py
osscs/backend/core/__init__.py
osscs/backend/core/have_socket.py
osscs/backend/core/socket_listener.py
osscs/backend/core/socket_reader.py
osscs/backend/core/socket_sender.py
osscs/backend/core/common/__init__.py
osscs/backend/core/common/base_listener.py
osscs/backend/core/common/base_reader.py
osscs/backend/core/common/base_sender.py
osscs/backend/models/__init__.py
osscs/backend/models/message.py
osscs/backend/models/message_preparer.py
osscs/backend/models/mode.py
osscs/backend/models/user.py
osscs/backend/models/common/__init__.py
osscs/backend/models/common/base_message_preparer.py
osscs/backend/models/common/base_user.py
osscs/backend/server/__init__.py
osscs/backend/server/message_listener.py
osscs/backend/server/common/__init__.py
osscs/backend/server/common/base_message_listener.py
osscs/backend/storage/__init__.py
osscs/backend/storage/address_storage.py
osscs/backend/storage/address_validator.py
osscs/backend/storage/key_storage.py
osscs/backend/storage/path_validator.py
osscs/backend/storage/uuid_storage.py
osscs/backend/storage/common/__init__.py
osscs/backend/storage/common/base_address.py
osscs/cryptography/core/__init__.py
osscs/cryptography/core/cryptor.py
osscs/cryptography/core/decryptor.py
osscs/cryptography/core/encryptor.py
osscs/cryptography/core/key_hasher.py
osscs/cryptography/core/key_loader.py
osscs/cryptography/core/signature_fabric.py
osscs/cryptography/core/signature_verifier.py
osscs/cryptography/core/common/__init__.py
osscs/cryptography/core/common/base_decryptor.py
osscs/cryptography/core/common/base_encryptor.py
osscs/cryptography/core/common/base_key_hasher.py
osscs/cryptography/core/common/base_key_loader.py
osscs/cryptography/core/common/base_rsa_keys.py
osscs/cryptography/core/common/base_signature_fabric.py
osscs-0.0.9.dist-info/LICENSE
osscs-0.0.9.dist-info/METADATA
osscs-0.0.9.dist-info/WHEEL
osscs-0.0.9.dist-info/top_level.txt
osscs-0.0.9.dist-info/RECORD
