Metadata-Version: 2.1
Name: osscs
Version: 0.0.9
Summary: Open-source crypto-secure communication system
Author-email: ImCocos <codimcocos@gmail.com>
Project-URL: Homepage, https://github.com/imcocos/ritatop
Project-URL: Issues, https://github.com/imcocos/ritatop/issues
Classifier: Programming Language :: Python :: 3
Classifier: License :: OSI Approved :: MIT License
Classifier: Operating System :: OS Independent
Requires-Python: >=3.11
License-File: LICENSE
Requires-Dist: cryptography >=42.0.3
Requires-Dist: pydantic >=2.6.4
